{
  "version": "7",
  "dialect": "postgresql",
  "entries": [
    {
      "idx": 0,
      "version": "7",
      "when": 1706550000000,
      "tag": "0000_init",
      "breakpoints": true
    },
    {
      "idx": 1,
      "version": "7",
      "when": 1738186800000,
      "tag": "0001_add_unique_constraints",
      "breakpoints": true
    },
    {
      "idx": 2,
      "version": "7",
      "when": 1738274400000,
      "tag": "0002_add_account_balances_unique",
      "breakpoints": true
    },
    {
      "idx": 3,
      "version": "7",
      "when": 1738360800000,
      "tag": "0003_add_monthly_values_unique",
      "breakpoints": true
    },
    {
      "idx": 4,
      "version": "7",
      "when": 1738447200000,
      "tag": "0004_add_yearly_budget",
      "breakpoints": true
    }
  ]
}
